{
  "id": "navigation",
  "label": "navigation",
  "repeatable": false,
  "status": true,
  "json": {
    "Main": {
      "navigationGroup": {
        "type": "Group",
        "config": {
          "label": "Navigation Group",
          "fields": {
            "navigationMenu": {
              "type": "StructuredText",
              "config": {
                "label": "Navigation Menu",
                "placeholder": "",
                "allowTargetBlank": true,
                "single": "paragraph,preformatted,heading1,heading2,heading3,heading4,heading5,heading6,strong,em,hyperlink,image,embed,list-item,o-list-item,rtl"
              }
            }
          }
        }
      }
    }
  }
}